{
  "41463101": {
    "regionCode": "41463101",
    "name": "신갈동",
    "parentName": "용인시 기흥구",
    "roads": [],
    "orderVolume": "중",
    "importance": 3,
    "landmarks": [],
    "fieldTips": [
      "신갈동 지역 인텔 데이터 추가 필요",
      "주요 도로, 랜드마크, 배달 특이사항을 입력해주세요."
    ]
  },
  "41463102": {
    "regionCode": "41463102",
    "name": "구갈동",
    "parentName": "용인시 기흥구",
    "roads": [],
    "orderVolume": "중",
    "importance": 3,
    "landmarks": [],
    "fieldTips": [
      "구갈동 지역 인텔 데이터 추가 필요",
      "주요 도로, 랜드마크, 배달 특이사항을 입력해주세요."
    ]
  },
  "41463103": {
    "regionCode": "41463103",
    "name": "상갈동",
    "parentName": "용인시 기흥구",
    "roads": [],
    "orderVolume": "중",
    "importance": 3,
    "landmarks": [],
    "fieldTips": [
      "상갈동 지역 인텔 데이터 추가 필요",
      "주요 도로, 랜드마크, 배달 특이사항을 입력해주세요."
    ]
  },
  "41463104": {
    "regionCode": "41463104",
    "name": "하갈동",
    "parentName": "용인시 기흥구",
    "roads": [],
    "orderVolume": "중",
    "importance": 3,
    "landmarks": [],
    "fieldTips": [
      "하갈동 지역 인텔 데이터 추가 필요",
      "주요 도로, 랜드마크, 배달 특이사항을 입력해주세요."
    ]
  },
  "41463105": {
    "regionCode": "41463105",
    "name": "보라동",
    "parentName": "용인시 기흥구",
    "roads": [],
    "orderVolume": "중",
    "importance": 3,
    "landmarks": [],
    "fieldTips": [
      "보라동 지역 인텔 데이터 추가 필요",
      "주요 도로, 랜드마크, 배달 특이사항을 입력해주세요."
    ]
  },
  "41463106": {
    "regionCode": "41463106",
    "name": "지곡동",
    "parentName": "용인시 기흥구",
    "roads": [],
    "orderVolume": "중",
    "importance": 3,
    "landmarks": [],
    "fieldTips": [
      "지곡동 지역 인텔 데이터 추가 필요",
      "주요 도로, 랜드마크, 배달 특이사항을 입력해주세요."
    ]
  },
  "41463107": {
    "regionCode": "41463107",
    "name": "공세동",
    "parentName": "용인시 기흥구",
    "roads": [],
    "orderVolume": "중",
    "importance": 3,
    "landmarks": [],
    "fieldTips": [
      "공세동 지역 인텔 데이터 추가 필요",
      "주요 도로, 랜드마크, 배달 특이사항을 입력해주세요."
    ]
  },
  "41463108": {
    "regionCode": "41463108",
    "name": "고매동",
    "parentName": "용인시 기흥구",
    "roads": [],
    "orderVolume": "중",
    "importance": 3,
    "landmarks": [],
    "fieldTips": [
      "고매동 지역 인텔 데이터 추가 필요",
      "주요 도로, 랜드마크, 배달 특이사항을 입력해주세요."
    ]
  },
  "41463109": {
    "regionCode": "41463109",
    "name": "농서동",
    "parentName": "용인시 기흥구",
    "roads": [],
    "orderVolume": "중",
    "importance": 3,
    "landmarks": [],
    "fieldTips": [
      "농서동 지역 인텔 데이터 추가 필요",
      "주요 도로, 랜드마크, 배달 특이사항을 입력해주세요."
    ]
  },
  "41463110": {
    "regionCode": "41463110",
    "name": "서천동",
    "parentName": "용인시 기흥구",
    "roads": [],
    "orderVolume": "중",
    "importance": 3,
    "landmarks": [],
    "fieldTips": [
      "서천동 지역 인텔 데이터 추가 필요",
      "주요 도로, 랜드마크, 배달 특이사항을 입력해주세요."
    ]
  },
  "41463111": {
    "regionCode": "41463111",
    "name": "영덕동",
    "parentName": "용인시 기흥구",
    "roads": [],
    "orderVolume": "중",
    "importance": 3,
    "landmarks": [],
    "fieldTips": [
      "영덕동 지역 인텔 데이터 추가 필요",
      "주요 도로, 랜드마크, 배달 특이사항을 입력해주세요."
    ]
  },
  "41463112": {
    "regionCode": "41463112",
    "name": "언남동",
    "parentName": "용인시 기흥구",
    "roads": [],
    "orderVolume": "중",
    "importance": 3,
    "landmarks": [],
    "fieldTips": [
      "언남동 지역 인텔 데이터 추가 필요",
      "주요 도로, 랜드마크, 배달 특이사항을 입력해주세요."
    ]
  },
  "41463113": {
    "regionCode": "41463113",
    "name": "마북동",
    "parentName": "용인시 기흥구",
    "roads": [],
    "orderVolume": "중",
    "importance": 3,
    "landmarks": [],
    "fieldTips": [
      "마북동 지역 인텔 데이터 추가 필요",
      "주요 도로, 랜드마크, 배달 특이사항을 입력해주세요."
    ]
  },
  "41463114": {
    "regionCode": "41463114",
    "name": "청덕동",
    "parentName": "용인시 기흥구",
    "roads": [],
    "orderVolume": "중",
    "importance": 3,
    "landmarks": [],
    "fieldTips": [
      "청덕동 지역 인텔 데이터 추가 필요",
      "주요 도로, 랜드마크, 배달 특이사항을 입력해주세요."
    ]
  },
  "41463115": {
    "regionCode": "41463115",
    "name": "동백동",
    "parentName": "용인시 기흥구",
    "roads": [],
    "orderVolume": "중",
    "importance": 3,
    "landmarks": [],
    "fieldTips": [
      "동백동 지역 인텔 데이터 추가 필요",
      "주요 도로, 랜드마크, 배달 특이사항을 입력해주세요."
    ]
  },
  "41463116": {
    "regionCode": "41463116",
    "name": "중동",
    "parentName": "용인시 기흥구",
    "roads": [],
    "orderVolume": "중",
    "importance": 3,
    "landmarks": [],
    "fieldTips": [
      "중동 지역 인텔 데이터 추가 필요",
      "주요 도로, 랜드마크, 배달 특이사항을 입력해주세요."
    ]
  },
  "41463117": {
    "regionCode": "41463117",
    "name": "상하동",
    "parentName": "용인시 기흥구",
    "roads": [],
    "orderVolume": "중",
    "importance": 3,
    "landmarks": [],
    "fieldTips": [
      "상하동 지역 인텔 데이터 추가 필요",
      "주요 도로, 랜드마크, 배달 특이사항을 입력해주세요."
    ]
  },
  "41463118": {
    "regionCode": "41463118",
    "name": "보정동",
    "parentName": "용인시 기흥구",
    "roads": [],
    "orderVolume": "중",
    "importance": 3,
    "landmarks": [],
    "fieldTips": [
      "보정동 지역 인텔 데이터 추가 필요",
      "주요 도로, 랜드마크, 배달 특이사항을 입력해주세요."
    ]
  }
}