{
  "2302051": {
    "regionCode": "2302051",
    "name": "만석동",
    "parentName": "인천 동구",
    "roads": [],
    "orderVolume": "중",
    "importance": 3,
    "landmarks": [],
    "fieldTips": [
      "만석동 지역 인텔 데이터 추가 필요",
      "주요 도로, 랜드마크, 배달 특이사항을 입력해주세요."
    ]
  },
  "2302052": {
    "regionCode": "2302052",
    "name": "화수1·화평동",
    "parentName": "인천 동구",
    "roads": [],
    "orderVolume": "중",
    "importance": 3,
    "landmarks": [],
    "fieldTips": [
      "화수1·화평동 지역 인텔 데이터 추가 필요",
      "주요 도로, 랜드마크, 배달 특이사항을 입력해주세요."
    ]
  },
  "2302053": {
    "regionCode": "2302053",
    "name": "화수2동",
    "parentName": "인천 동구",
    "roads": [],
    "orderVolume": "중",
    "importance": 3,
    "landmarks": [],
    "fieldTips": [
      "화수2동 지역 인텔 데이터 추가 필요",
      "주요 도로, 랜드마크, 배달 특이사항을 입력해주세요."
    ]
  },
  "2302055": {
    "regionCode": "2302055",
    "name": "송현1·2동",
    "parentName": "인천 동구",
    "roads": [],
    "orderVolume": "중",
    "importance": 3,
    "landmarks": [],
    "fieldTips": [
      "송현1·2동 지역 인텔 데이터 추가 필요",
      "주요 도로, 랜드마크, 배달 특이사항을 입력해주세요."
    ]
  },
  "2302057": {
    "regionCode": "2302057",
    "name": "송현3동",
    "parentName": "인천 동구",
    "roads": [],
    "orderVolume": "중",
    "importance": 3,
    "landmarks": [],
    "fieldTips": [
      "송현3동 지역 인텔 데이터 추가 필요",
      "주요 도로, 랜드마크, 배달 특이사항을 입력해주세요."
    ]
  },
  "2302058": {
    "regionCode": "2302058",
    "name": "송림1동",
    "parentName": "인천 동구",
    "roads": [],
    "orderVolume": "중",
    "importance": 3,
    "landmarks": [],
    "fieldTips": [
      "송림1동 지역 인텔 데이터 추가 필요",
      "주요 도로, 랜드마크, 배달 특이사항을 입력해주세요."
    ]
  },
  "2302059": {
    "regionCode": "2302059",
    "name": "송림2동",
    "parentName": "인천 동구",
    "roads": [],
    "orderVolume": "중",
    "importance": 3,
    "landmarks": [],
    "fieldTips": [
      "송림2동 지역 인텔 데이터 추가 필요",
      "주요 도로, 랜드마크, 배달 특이사항을 입력해주세요."
    ]
  },
  "2302060": {
    "regionCode": "2302060",
    "name": "송림3·5동",
    "parentName": "인천 동구",
    "roads": [],
    "orderVolume": "중",
    "importance": 3,
    "landmarks": [],
    "fieldTips": [
      "송림3·5동 지역 인텔 데이터 추가 필요",
      "주요 도로, 랜드마크, 배달 특이사항을 입력해주세요."
    ]
  },
  "2302061": {
    "regionCode": "2302061",
    "name": "송림4동",
    "parentName": "인천 동구",
    "roads": [],
    "orderVolume": "중",
    "importance": 3,
    "landmarks": [],
    "fieldTips": [
      "송림4동 지역 인텔 데이터 추가 필요",
      "주요 도로, 랜드마크, 배달 특이사항을 입력해주세요."
    ]
  },
  "2302063": {
    "regionCode": "2302063",
    "name": "송림6동",
    "parentName": "인천 동구",
    "roads": [],
    "orderVolume": "중",
    "importance": 3,
    "landmarks": [],
    "fieldTips": [
      "송림6동 지역 인텔 데이터 추가 필요",
      "주요 도로, 랜드마크, 배달 특이사항을 입력해주세요."
    ]
  },
  "2302064": {
    "regionCode": "2302064",
    "name": "금창동",
    "parentName": "인천 동구",
    "roads": [],
    "orderVolume": "중",
    "importance": 3,
    "landmarks": [],
    "fieldTips": [
      "금창동 지역 인텔 데이터 추가 필요",
      "주요 도로, 랜드마크, 배달 특이사항을 입력해주세요."
    ]
  }
}